{
  "parent": "minecraft:recipes/root",
  "criteria": {
    "has_the_recipe": {
      "conditions": {
        "recipe": "thedirtystuff:tobacco_leaves"
      },
      "trigger": "minecraft:recipe_unlocked"
    },
    "has_tobacco_package": {
      "conditions": {
        "items": [
          {
            "items": "thedirtystuff:tobacco_leaves_package"
          }
        ]
      },
      "trigger": "minecraft:inventory_changed"
    }
  },
  "requirements": [
    [
      "has_the_recipe",
      "has_tobacco_package"
    ]
  ],
  "rewards": {
    "recipes": [
      "thedirtystuff:tobacco_leaves"
    ]
  }
}